{


    "DB_AppData":[

        {

            "appversion":"8.0",
            "updatemessage":"Fix Force Close. Change UI Design.",
            "channelURL":"https://mctvteam.github.io/Coder/Data/tvchannel.json",
            "movieURL":"https://mctvteam.github.io/Coder/Data/movies.json",
            "seriesURL":"https://mctvteam.github.io/Coder/Data/series.json",
            "sliderURL":"https://mctvteam.github.io/Coder/Ads/ads.json",            
            "directDownload":"https://mctvteam.github.io/Coder/Download/mctv8.0.apk"
            
            
        }
    ]
}
